AndTools/Pack.py
AndTools/TEA.py
AndTools/__init__.py
AndTools/byte_.py
Jce/__init__.py
Jce/bytebuffer.py
Jce/exception.py
Jce/stream.py
Jce/struct.py
Jce_b/__init__.py
Jce_b/buffer.py
Jce_b/head.py
Jce_b/jcetypes.py
Jce_b/reader.py
Jce_b/struct.py
Jce_b/typing.py
Jce_b/writer.py
pyproto/__init__.py
MDQTools-0.2.8.dist-info/METADATA
MDQTools-0.2.8.dist-info/WHEEL
MDQTools-0.2.8.dist-info/top_level.txt
MDQTools-0.2.8.dist-info/RECORD
