Metadata-Version: 2.1
Name: MDQTools
Version: 0.2.8
Summary: Android Tools for Python
Home-page: 
Author: Magpie Bridge
Author-email: 
Classifier: Programming Language :: Python :: 3
Classifier: License :: OSI Approved :: MIT License
Classifier: Operating System :: OS Independent
